opencv_auxiliary_for_vscode/__init__.py
opencv_auxiliary_for_vscode/starting_template.py
opencv_auxiliary_for_vscode-0.0.5.dist-info/METADATA
opencv_auxiliary_for_vscode-0.0.5.dist-info/WHEEL
opencv_auxiliary_for_vscode-0.0.5.dist-info/top_level.txt
opencv_auxiliary_for_vscode-0.0.5.dist-info/RECORD
