Metadata-Version: 2.1
Name: opencv-auxiliary-for-vscode
Version: 0.0.5
Summary: tools to work with opencv on vscode
Home-page: UNKNOWN
Author: tms1991
Author-email: <youremail@email.com>
License: UNKNOWN
Keywords: opencv,vscode
Platform: UNKNOWN
Classifier: Development Status :: 3 - Alpha
Classifier: Intended Audience :: Education
Classifier: Programming Language :: Python :: 2
Classifier: Programming Language :: Python :: 3
Classifier: Operating System :: MacOS :: MacOS X
Classifier: Operating System :: Microsoft :: Windows
Requires-Dist: matplotlib
Requires-Dist: numpy
Requires-Dist: opencv-python
